gideon_api/__init__.py
gideon_api/lookup_id_code.py
gideon_api/diseases/__init__.py
gideon_api/diseases/filter.py
gideon_api/diseases/outbreaks.py
gideon_api/query/__init__.py
gideon_api/query/api_wrapper.py
gideon_api/query/cache.py
gideon_api/utilities/__init__.py
gideon_api/utilities/geospatial.py
gideon_api-0.3.0.dist-info/LICENSE
gideon_api-0.3.0.dist-info/METADATA
gideon_api-0.3.0.dist-info/WHEEL
gideon_api-0.3.0.dist-info/top_level.txt
gideon_api-0.3.0.dist-info/RECORD
