Metadata-Version: 2.1
Name: gideon-api
Version: 0.3.0
Summary: GIDEON provides epidemiological data going back to 1348 AD. This package provides an interface with the GIDEON API to access its Infectous Disease database within Python.
Home-page: https://gideononline.github.io/gideon-api-python-docs
Author: GIDEON Informatics
Author-email: info@gideononline.com
License: Mozilla Public License Version 2.0
Project-URL: GitHub, https://github.com/gideononline/gideon-api-python
Project-URL: Documentation, https://gideononline.github.io/gideon-api-python-docs
Project-URL: GIDEON, https://www.gideononline.com/
Platform: UNKNOWN
Classifier: Programming Language :: Python :: 3
Classifier: License :: OSI Approved :: Mozilla Public License 2.0 (MPL 2.0)
Classifier: Operating System :: OS Independent
Classifier: Intended Audience :: Healthcare Industry
Classifier: Topic :: Scientific/Engineering :: Medical Science Apps.
Requires-Python: >=3.6
License-File: LICENSE
Requires-Dist: requests
Requires-Dist: pandas
Requires-Dist: geopandas
